README.md
setup.cfg
setup.py
ssmx.py
ssmx.egg-info/PKG-INFO
ssmx.egg-info/SOURCES.txt
ssmx.egg-info/dependency_links.txt
ssmx.egg-info/entry_points.txt
ssmx.egg-info/requires.txt
ssmx.egg-info/top_level.txt