Metadata-Version: 2.1
Name: ssmx
Version: 1.0.1
Summary: CLI tool for injecting parameters stored in AWS SSM into executables.
Home-page: https://github.com/JetJet13/ssmx
Author: Johny Georges
Author-email: jgeorges371@gmail.com
License: UNKNOWN
Download-URL: https://github.com/JetJet13/ssmx/archive/v1.0.1.tar.gz
Platform: UNKNOWN
Requires-Python: >=2.7
